README.rst
setup.cfg
setup.py
ExtractionTool/DataExtractionTool.py
ExtractionTool/__ini__.py
ExtractionTool.egg-info/PKG-INFO
ExtractionTool.egg-info/SOURCES.txt
ExtractionTool.egg-info/dependency_links.txt
ExtractionTool.egg-info/top_level.txt
ExtractionTool.egg-info/zip-safe