Metadata-Version: 1.1
Name: ExtractionTool
Version: 1.0.20
Summary: this is a test package.
Home-page: https://github.com/yanyundoris/DataExtraction
Author: YanyunDoris
Author-email: dorisliu9318@gmail.com
License: MIT
Download-URL: https://github.com/yanyundoris/DataExtraction/archive/0.1.tar.gz
Keywords: test python package
Platform: UNKNOWN
Classifier: License :: OSI Approved :: MIT License
Classifier: Programming Language :: Python
Classifier: Intended Audience :: Developers
Classifier: Operating System :: OS Independent
